{
  "date": "2026-07-02",
  "last_run": "2026-07-02T09:50:51.712901+05:30",
  "token_valid": true,
  "token_refreshed_at": "2026-07-02T09:05:43.608833+05:30",
  "instruments": [
    {
      "ce": {
        "c1": true,
        "c2": false,
        "c3": false,
        "c4": false,
        "signal": false
      },
      "pe": {
        "c1": false,
        "c2": false,
        "c3": false,
        "c4": false,
        "signal": false
      },
      "futures_price": 24225.0,
      "candle_high": 24240.0,
      "candle_low": 24225.0,
      "prev_candle_high": 24247.0,
      "prev_candle_low": 24229.0,
      "candle_time": "09:45 IST",
      "vwap": 24208.375950081314,
      "rsi": 68.42339100420472,
      "pdi": 37.46144104452103,
      "ndi": 9.650766588262856,
      "live_price": 24225.2,
      "live_vwap": 24206.58,
      "live_rsi": 68.45409961272787,
      "live_pdi": 37.43815710986367,
      "live_ndi": 9.64476821200265,
      "atm_strike": 24200,
      "name": "NIFTY",
      "symbol": "NIFTY26JULFUT",
      "strike_step": 50
    },
    {
      "ce": {
        "c1": false,
        "c2": false,
        "c3": false,
        "c4": false,
        "signal": false
      },
      "pe": {
        "c1": true,
        "c2": false,
        "c3": true,
        "c4": false,
        "signal": false
      },
      "futures_price": 58649.0,
      "candle_high": 58679.0,
      "candle_low": 58612.2,
      "prev_candle_high": 58669.0,
      "prev_candle_low": 58613.8,
      "candle_time": "09:45 IST",
      "vwap": 58545.19887398576,
      "rsi": 73.55039230103662,
      "pdi": 38.0911385868176,
      "ndi": 13.799246778656395,
      "live_price": 58626.2,
      "live_vwap": 58538.86,
      "live_rsi": 70.58804462083629,
      "live_pdi": 37.15587075323232,
      "live_ndi": 13.460428037117143,
      "atm_strike": 58600,
      "name": "BANKNIFTY",
      "symbol": "BANKNIFTY26JULFUT",
      "strike_step": 100
    },
    {
      "ce": {
        "c1": false,
        "c2": false,
        "c3": false,
        "c4": false,
        "signal": false
      },
      "pe": {
        "c1": true,
        "c2": false,
        "c3": true,
        "c4": false,
        "signal": false
      },
      "futures_price": 77800.0,
      "candle_high": 77805.0,
      "candle_low": 77780.0,
      "prev_candle_high": 77820.0,
      "prev_candle_low": 77789.65,
      "candle_time": "09:45 IST",
      "vwap": 77700.25032467532,
      "rsi": 72.01361963020364,
      "pdi": 39.07169322902086,
      "ndi": 9.597911091555602,
      "live_price": 77799.9,
      "live_vwap": 77696.23,
      "live_rsi": 72.00128831283432,
      "live_pdi": 39.06735873997868,
      "live_ndi": 9.596846329908075,
      "atm_strike": 77800,
      "name": "SENSEX",
      "symbol": "SENSEX26JULFUT",
      "strike_step": 100
    }
  ],
  "active_signals": [],
  "history": [
    {
      "time": "09:40",
      "instrument": "BANKNIFTY",
      "ce_conditions": [
        true,
        true,
        true,
        true
      ],
      "pe_conditions": [
        false,
        false,
        false,
        false
      ],
      "ce_signal": true,
      "pe_signal": false,
      "rsi": 72.78214116895649,
      "pdi": 37.94593602771311,
      "ndi": 15.699279170830716,
      "price": 58625.2
    }
  ],
  "_meta": "Seed file. Will be overwritten by morning-login.yml on first run."
}