{
  "date": "2026-07-21",
  "last_run": "2026-07-21T10:45:44.274318+05:30",
  "token_valid": true,
  "token_refreshed_at": "2026-07-21T09:05:37.017433+05:30",
  "instruments": [
    {
      "ce": {
        "c1": false,
        "c2": false,
        "c3": false,
        "c4": false,
        "c5": false,
        "signal": false
      },
      "pe": {
        "c1": true,
        "c2": false,
        "c3": false,
        "c4": false,
        "c5": true,
        "signal": false
      },
      "futures_price": 24185.0,
      "candle_high": 24195.3,
      "candle_low": 24170.0,
      "prev_candle_high": 24193.0,
      "prev_candle_low": 24171.0,
      "candle_time": "10:40 IST",
      "vwap": 24229.122467376368,
      "rsi": 35.69457494633326,
      "pdi": 5.163651633999643,
      "ndi": 23.378205039941186,
      "live_price": 24176.3,
      "live_vwap": 24231.46,
      "live_rsi": 33.38893057723941,
      "live_pdi": 5.013159244532757,
      "live_ndi": 22.69685738380924,
      "atm_strike": 24200,
      "name": "NIFTY",
      "symbol": "NIFTY26JULFUT",
      "strike_step": 50
    },
    {
      "ce": {
        "c1": false,
        "c2": false,
        "c3": false,
        "c4": false,
        "c5": true,
        "signal": false
      },
      "pe": {
        "c1": false,
        "c2": false,
        "c3": false,
        "c4": false,
        "c5": false,
        "signal": false
      },
      "futures_price": 58030.0,
      "candle_high": 58049.8,
      "candle_low": 57991.0,
      "prev_candle_high": 58069.6,
      "prev_candle_low": 57978.0,
      "candle_time": "10:40 IST",
      "vwap": 58130.75909007014,
      "rsi": 44.21801558489215,
      "pdi": 11.326243106744599,
      "ndi": 18.34845182093926,
      "live_price": 58030.0,
      "live_vwap": 58134.8,
      "live_rsi": 44.21801558489215,
      "live_pdi": 11.326243106744599,
      "live_ndi": 18.34845182093926,
      "atm_strike": 58000,
      "name": "BANKNIFTY",
      "symbol": "BANKNIFTY26JULFUT",
      "strike_step": 100
    },
    {
      "ce": {
        "c1": false,
        "c2": false,
        "c3": false,
        "c4": false,
        "c5": false,
        "signal": false
      },
      "pe": {
        "c1": false,
        "c2": false,
        "c3": false,
        "c4": false,
        "c5": true,
        "signal": false
      },
      "futures_price": 77549.35,
      "candle_high": 77567.15,
      "candle_low": 77527.3,
      "prev_candle_high": 77567.15,
      "prev_candle_low": 77527.0,
      "candle_time": "10:40 IST",
      "vwap": 77644.04933333333,
      "rsi": 37.83139811831035,
      "pdi": 10.925366053782739,
      "ndi": 26.14952228077044,
      "live_price": 77549.35,
      "live_vwap": 77647.89,
      "live_rsi": 37.83139811831035,
      "live_pdi": 10.925366053782737,
      "live_ndi": 26.14952228077044,
      "atm_strike": 77500,
      "name": "SENSEX",
      "symbol": "SENSEX26JULFUT",
      "strike_step": 100
    },
    {
      "name": "NIFTY",
      "symbol": "NIFTY26JULFUT",
      "strike_step": 50,
      "ce": {
        "c1": false,
        "c2": false,
        "c3": false,
        "c4": false,
        "c5": null,
        "signal": false
      },
      "pe": {
        "c1": false,
        "c2": false,
        "c3": false,
        "c4": false,
        "c5": null,
        "signal": false
      },
      "futures_price": 24185.0,
      "vwap": 24231.46,
      "rsi": 35.69457494633326,
      "pdi": null,
      "ndi": null,
      "atm_strike": 24200,
      "candle_time": "10:40 IST",
      "prev_candle_low": 24170.0,
      "prev_candle_high": 24195.3,
      "strategy": "PVWAP",
      "pvwap_bias": "NEUTRAL",
      "pvwap_rationale": "neutral"
    }
  ],
  "active_signals": [],
  "history": [],
  "_meta": "Seed file. Will be overwritten by morning-login.yml on first run."
}