{
  "date": "2026-06-29",
  "last_run": "2026-06-29T13:15:57.001962+05:30",
  "token_valid": true,
  "instruments": [
    {
      "name": "RELIANCE",
      "sector": "Energy/Conglomerate",
      "lot_size": 250,
      "ce": {
        "c1": false,
        "c2": false,
        "c3": false,
        "c4": false,
        "signal": false
      },
      "pe": {
        "c1": true,
        "c2": false,
        "c3": true,
        "c4": false,
        "signal": false
      },
      "futures_price": 1300.7,
      "candle_high": 1302.2,
      "candle_low": 1300.6,
      "prev_candle_high": 1302.0,
      "prev_candle_low": 1300.3,
      "candle_time": "13:10 IST",
      "vwap": 1307.0295501257026,
      "rsi": 34.32109592178014,
      "pdi": 9.500078904563363,
      "ndi": 25.48987293735059,
      "live_price": 1300.5,
      "live_vwap": 1307.19,
      "live_rsi": 33.70073760752089,
      "live_pdi": 9.417567566183603,
      "live_ndi": 25.702751525845365,
      "atm_strike": 1300,
      "strike_step": 50
    },
    {
      "name": "ICICIBANK",
      "sector": "Private Banking",
      "lot_size": 700,
      "ce": {
        "c1": false,
        "c2": false,
        "c3": false,
        "c4": false,
        "signal": false
      },
      "pe": {
        "c1": true,
        "c2": true,
        "c3": true,
        "c4": false,
        "signal": false
      },
      "futures_price": 1388.9,
      "candle_high": 1390.1,
      "candle_low": 1388.3,
      "prev_candle_high": 1390.0,
      "prev_candle_low": 1387.9,
      "candle_time": "13:10 IST",
      "vwap": 1390.0420557706555,
      "rsi": 53.30316896488145,
      "pdi": 23.235240090951702,
      "ndi": 13.13184659733119,
      "live_price": 1388.5,
      "live_vwap": 1390.33,
      "live_rsi": 51.926611689847874,
      "live_pdi": 22.89615967117686,
      "live_ndi": 12.940208721449038,
      "atm_strike": 1380,
      "strike_step": 20
    },
    {
      "name": "INFY",
      "sector": "IT",
      "lot_size": 400,
      "ce": {
        "c1": false,
        "c2": false,
        "c3": false,
        "c4": false,
        "signal": false
      },
      "pe": {
        "c1": true,
        "c2": false,
        "c3": true,
        "c4": true,
        "signal": false
      },
      "futures_price": 1031.9,
      "candle_high": 1034.0,
      "candle_low": 1031.6,
      "prev_candle_high": 1034.6,
      "prev_candle_low": 1033.6,
      "candle_time": "13:10 IST",
      "vwap": 1034.211807064015,
      "rsi": 42.998836538347405,
      "pdi": 16.72147518476523,
      "ndi": 23.08051297548621,
      "live_price": 1031.1,
      "live_vwap": 1034.51,
      "live_rsi": 39.972713892917795,
      "live_pdi": 16.165033616821656,
      "live_ndi": 24.392277692718114,
      "atm_strike": 1040,
      "strike_step": 20
    },
    {
      "name": "BAJFINANCE",
      "sector": "NBFC",
      "lot_size": 125,
      "ce": {
        "c1": false,
        "c2": false,
        "c3": false,
        "c4": false,
        "signal": false
      },
      "pe": {
        "c1": true,
        "c2": false,
        "c3": false,
        "c4": false,
        "signal": false
      },
      "futures_price": 982.85,
      "candle_high": 983.2,
      "candle_low": 981.7,
      "prev_candle_high": 981.95,
      "prev_candle_low": 980.7,
      "candle_time": "13:10 IST",
      "vwap": 985.6883377911773,
      "rsi": 45.822146507400085,
      "pdi": 19.261988263590183,
      "ndi": 24.12954170091934,
      "live_price": 982.35,
      "live_vwap": 985.39,
      "live_rsi": 43.762623656477736,
      "live_pdi": 18.87583116741648,
      "live_ndi": 23.64580172414642,
      "atm_strike": 1000,
      "strike_step": 100
    },
    {
      "name": "SUNPHARMA",
      "sector": "Pharma",
      "lot_size": 400,
      "ce": {
        "c1": true,
        "c2": false,
        "c3": false,
        "c4": false,
        "signal": false
      },
      "pe": {
        "c1": false,
        "c2": false,
        "c3": false,
        "c4": false,
        "signal": false
      },
      "futures_price": 1877.1,
      "candle_high": 1879.2,
      "candle_low": 1876.5,
      "prev_candle_high": 1880.9,
      "prev_candle_low": 1878.2,
      "candle_time": "13:10 IST",
      "vwap": 1887.4167431013898,
      "rsi": 33.50042597313714,
      "pdi": 13.847884176294913,
      "ndi": 31.265182403296695,
      "live_price": 1877.3,
      "live_vwap": 1887.08,
      "live_rsi": 34.152866690241595,
      "live_pdi": 13.775287252814582,
      "live_ndi": 31.10127606023123,
      "atm_strike": 1880,
      "strike_step": 20
    },
    {
      "name": "LT",
      "sector": "Engineering/Infra",
      "lot_size": 175,
      "ce": {
        "c1": false,
        "c2": false,
        "c3": false,
        "c4": false,
        "signal": false
      },
      "pe": {
        "c1": true,
        "c2": false,
        "c3": true,
        "c4": false,
        "signal": false
      },
      "futures_price": 4199.4,
      "candle_high": 4206.0,
      "candle_low": 4196.9,
      "prev_candle_high": 4208.0,
      "prev_candle_low": 4188.0,
      "candle_time": "13:10 IST",
      "vwap": 4218.571841743307,
      "rsi": 52.67159087812002,
      "pdi": 30.197343624055495,
      "ndi": 22.173329988347703,
      "live_price": 4194.0,
      "live_vwap": 4218.83,
      "live_rsi": 48.98173099271609,
      "live_pdi": 28.88140982217311,
      "live_ndi": 23.547354308982445,
      "atm_strike": 4200,
      "strike_step": 50
    },
    {
      "name": "SBIN",
      "sector": "PSU Banking",
      "lot_size": 750,
      "ce": {
        "c1": false,
        "c2": false,
        "c3": false,
        "c4": false,
        "signal": false
      },
      "pe": {
        "c1": true,
        "c2": false,
        "c3": true,
        "c4": false,
        "signal": false
      },
      "futures_price": 1032.6,
      "candle_high": 1033.4,
      "candle_low": 1032.2,
      "prev_candle_high": 1033.55,
      "prev_candle_low": 1032.0,
      "candle_time": "13:10 IST",
      "vwap": 1039.915342030072,
      "rsi": 36.256361967588134,
      "pdi": 8.351214050719367,
      "ndi": 25.642340622066005,
      "live_price": 1032.05,
      "live_vwap": 1040.03,
      "live_rsi": 34.566724203735845,
      "live_pdi": 8.153740486652614,
      "live_ndi": 25.68089289252169,
      "atm_strike": 1030,
      "strike_step": 10
    },
    {
      "name": "BHARTIARTL",
      "sector": "Telecom",
      "lot_size": 475,
      "ce": {
        "c1": false,
        "c2": false,
        "c3": false,
        "c4": false,
        "signal": false
      },
      "pe": {
        "c1": true,
        "c2": false,
        "c3": false,
        "c4": false,
        "signal": false
      },
      "futures_price": 1838.0,
      "candle_high": 1839.5,
      "candle_low": 1836.3,
      "prev_candle_high": 1838.8,
      "prev_candle_low": 1836.1,
      "candle_time": "13:10 IST",
      "vwap": 1840.176194625502,
      "rsi": 45.57500143345783,
      "pdi": 19.47942971983268,
      "ndi": 20.70358413154679,
      "live_price": 1836.3,
      "live_vwap": 1840.0,
      "live_rsi": 41.819407638661104,
      "live_pdi": 18.67872471398412,
      "live_ndi": 19.85256006710725,
      "atm_strike": 1840,
      "strike_step": 20
    },
    {
      "name": "TATASTEEL",
      "sector": "Metals",
      "lot_size": 2750,
      "ce": {
        "c1": false,
        "c2": false,
        "c3": false,
        "c4": false,
        "signal": false
      },
      "pe": {
        "c1": true,
        "c2": false,
        "c3": false,
        "c4": false,
        "signal": false
      },
      "futures_price": 189.62,
      "candle_high": 189.77,
      "candle_low": 189.5,
      "prev_candle_high": 189.62,
      "prev_candle_low": 189.3,
      "candle_time": "13:10 IST",
      "vwap": 190.2623618286105,
      "rsi": 41.864799067439144,
      "pdi": 18.874022664209992,
      "ndi": 29.169480551229775,
      "live_price": 189.55,
      "live_vwap": 190.25,
      "live_rsi": 40.73260820253721,
      "live_pdi": 18.611127960725597,
      "live_ndi": 28.76318126481157,
      "atm_strike": 190.0,
      "strike_step": 2.5
    },
    {
      "name": "ASIANPAINT",
      "sector": "Paints/Consumer",
      "lot_size": 250,
      "ce": {
        "c1": false,
        "c2": false,
        "c3": false,
        "c4": false,
        "signal": false
      },
      "pe": {
        "c1": true,
        "c2": false,
        "c3": true,
        "c4": false,
        "signal": false
      },
      "futures_price": 2648.4,
      "candle_high": 2652.8,
      "candle_low": 2648.4,
      "prev_candle_high": 2654.3,
      "prev_candle_low": 2650.2,
      "candle_time": "13:10 IST",
      "vwap": 2656.903807688495,
      "rsi": 49.50947429158883,
      "pdi": 18.63640426866475,
      "ndi": 15.973467817986503,
      "live_price": 2647.6,
      "live_vwap": 2656.76,
      "live_rsi": 48.24382347067669,
      "live_pdi": 18.404936801923736,
      "live_ndi": 17.017092342482652,
      "atm_strike": 2640,
      "strike_step": 20
    },
    {
      "name": "AXISBANK",
      "sector": "Private Banking",
      "lot_size": 625,
      "ce": {
        "c1": false,
        "c2": false,
        "c3": false,
        "c4": false,
        "signal": false
      },
      "pe": {
        "c1": true,
        "c2": false,
        "c3": false,
        "c4": false,
        "signal": false
      },
      "futures_price": 1379.0,
      "candle_high": 1379.9,
      "candle_low": 1378.6,
      "prev_candle_high": 1379.5,
      "prev_candle_low": 1376.6,
      "candle_time": "13:10 IST",
      "vwap": 1382.8412246392395,
      "rsi": 52.93622386522659,
      "pdi": 25.655055130797372,
      "ndi": 23.545846187507056,
      "live_price": 1378.3,
      "live_vwap": 1383.86,
      "live_rsi": 51.16699740757563,
      "live_pdi": 25.143210060212265,
      "live_ndi": 23.93112666952361,
      "atm_strike": 1380,
      "strike_step": 10
    },
    {
      "name": "MARUTI",
      "sector": "Auto",
      "lot_size": 50,
      "ce": {
        "c1": false,
        "c2": false,
        "c3": false,
        "c4": false,
        "signal": false
      },
      "pe": {
        "c1": true,
        "c2": false,
        "c3": true,
        "c4": false,
        "signal": false
      },
      "futures_price": 13448.0,
      "candle_high": 13475.0,
      "candle_low": 13432.0,
      "prev_candle_high": 13475.0,
      "prev_candle_low": 13442.0,
      "candle_time": "13:10 IST",
      "vwap": 13585.76657893945,
      "rsi": 33.08117360755509,
      "pdi": 11.9911691277007,
      "ndi": 28.26130921321895,
      "live_price": 13441.0,
      "live_vwap": 13587.76,
      "live_rsi": 32.0928757612313,
      "live_pdi": 11.794770917708407,
      "live_ndi": 27.798429365357173,
      "atm_strike": 13400,
      "strike_step": 100
    },
    {
      "name": "CIPLA",
      "sector": "Pharma",
      "lot_size": 375,
      "ce": {
        "c1": true,
        "c2": false,
        "c3": true,
        "c4": false,
        "signal": false
      },
      "pe": {
        "c1": false,
        "c2": false,
        "c3": false,
        "c4": false,
        "signal": false
      },
      "futures_price": 1471.8,
      "candle_high": 1471.8,
      "candle_low": 1467.0,
      "prev_candle_high": 1475.0,
      "prev_candle_low": 1468.6,
      "candle_time": "13:10 IST",
      "vwap": 1477.3192019405037,
      "rsi": 37.65678498489134,
      "pdi": 10.738123911588936,
      "ndi": 38.11546161524847,
      "live_price": 1473.9,
      "live_vwap": 1477.04,
      "live_rsi": 43.0669554220748,
      "live_pdi": 14.877945223775772,
      "live_ndi": 36.34772820840905,
      "atm_strike": 1470,
      "strike_step": 10
    },
    {
      "name": "HINDALCO",
      "sector": "Metals",
      "lot_size": 700,
      "ce": {
        "c1": false,
        "c2": false,
        "c3": false,
        "c4": false,
        "signal": false
      },
      "pe": {
        "c1": true,
        "c2": false,
        "c3": true,
        "c4": false,
        "signal": false
      },
      "futures_price": 966.8,
      "candle_high": 968.5,
      "candle_low": 966.4,
      "prev_candle_high": 968.4,
      "prev_candle_low": 966.0,
      "candle_time": "13:10 IST",
      "vwap": 965.5799716226109,
      "rsi": 44.276861700403174,
      "pdi": 14.191742713468843,
      "ndi": 23.874778328919604,
      "live_price": 965.9,
      "live_vwap": 965.18,
      "live_rsi": 40.480962864798734,
      "live_pdi": 13.676561820782924,
      "live_ndi": 25.02483660027713,
      "atm_strike": 970,
      "strike_step": 10
    }
  ],
  "active_signals": [],
  "history": [
    {
      "time": "10:51",
      "candle_time": "10:45 IST",
      "instrument": "RELIANCE",
      "ce_conditions": [
        false,
        false,
        false,
        false
      ],
      "pe_conditions": [
        true,
        true,
        true,
        true
      ],
      "ce_signal": false,
      "pe_signal": true,
      "rsi": 35.59666594056793,
      "pdi": 12.9229248252954,
      "ndi": 32.26059194695167,
      "price": 1308.8
    },
    {
      "time": "10:35",
      "candle_time": "10:30 IST",
      "instrument": "INFY",
      "ce_conditions": [
        false,
        false,
        false,
        false
      ],
      "pe_conditions": [
        true,
        true,
        true,
        true
      ],
      "ce_signal": false,
      "pe_signal": true,
      "rsi": 45.017758076319886,
      "pdi": 24.980564605655918,
      "ndi": 25.668602569126897,
      "price": 1035.2
    },
    {
      "time": "10:25",
      "candle_time": "10:20 IST",
      "instrument": "AXISBANK",
      "ce_conditions": [
        true,
        true,
        true,
        true
      ],
      "pe_conditions": [
        false,
        false,
        false,
        false
      ],
      "ce_signal": true,
      "pe_signal": false,
      "rsi": 63.14183536553819,
      "pdi": 32.81689407613039,
      "ndi": 10.88676971324907,
      "price": 1390.3
    }
  ]
}