{
  "date": "2026-07-03",
  "last_run": "2026-07-03T11:51:05.443676+05:30",
  "token_valid": true,
  "instruments": [
    {
      "name": "RELIANCE",
      "sector": "Energy/Conglomerate",
      "lot_size": 250,
      "ce": {
        "c1": false,
        "c2": true,
        "c3": false,
        "c4": false,
        "signal": false
      },
      "pe": {
        "c1": true,
        "c2": false,
        "c3": false,
        "c4": false,
        "signal": false
      },
      "futures_price": 1306.4,
      "candle_high": 1307.0,
      "candle_low": 1305.0,
      "prev_candle_high": 1307.0,
      "prev_candle_low": 1305.2,
      "candle_time": "11:45 IST",
      "vwap": 1305.305631009352,
      "rsi": 60.8048238155863,
      "pdi": 22.582728681060647,
      "ndi": 13.882339745297838,
      "live_price": 1306.3,
      "live_vwap": 1305.39,
      "live_rsi": 60.13826287853266,
      "live_pdi": 22.478108268198564,
      "live_ndi": 13.818026165829346,
      "atm_strike": 1300,
      "strike_step": 50
    },
    {
      "name": "ICICIBANK",
      "sector": "Private Banking",
      "lot_size": 700,
      "ce": {
        "c1": false,
        "c2": false,
        "c3": false,
        "c4": false,
        "signal": false
      },
      "pe": {
        "c1": true,
        "c2": true,
        "c3": false,
        "c4": false,
        "signal": false
      },
      "futures_price": 1412.3,
      "candle_high": 1413.1,
      "candle_low": 1411.1,
      "prev_candle_high": 1412.4,
      "prev_candle_low": 1410.6,
      "candle_time": "11:45 IST",
      "vwap": 1412.4153805529484,
      "rsi": 56.90250784637877,
      "pdi": 21.756730307462735,
      "ndi": 17.314730009103123,
      "live_price": 1411.9,
      "live_vwap": 1412.47,
      "live_rsi": 54.84446511508072,
      "live_pdi": 21.429865810572505,
      "live_ndi": 17.05460036493162,
      "atm_strike": 1420,
      "strike_step": 20
    },
    {
      "name": "INFY",
      "sector": "IT",
      "lot_size": 400,
      "ce": {
        "c1": false,
        "c2": false,
        "c3": false,
        "c4": false,
        "signal": false
      },
      "pe": {
        "c1": true,
        "c2": false,
        "c3": true,
        "c4": false,
        "signal": false
      },
      "futures_price": 1053.1,
      "candle_high": 1054.3,
      "candle_low": 1052.7,
      "prev_candle_high": 1054.9,
      "prev_candle_low": 1053.4,
      "candle_time": "11:45 IST",
      "vwap": 1052.0042999116672,
      "rsi": 57.74411910294528,
      "pdi": 28.8195139412452,
      "ndi": 15.144027672807358,
      "live_price": 1052.6,
      "live_vwap": 1052.57,
      "live_rsi": 56.171239985719026,
      "live_pdi": 28.403818089652606,
      "live_ndi": 15.214070753894326,
      "atm_strike": 1060,
      "strike_step": 20
    },
    {
      "name": "BAJFINANCE",
      "sector": "NBFC",
      "lot_size": 125,
      "ce": {
        "c1": true,
        "c2": false,
        "c3": true,
        "c4": false,
        "signal": false
      },
      "pe": {
        "c1": false,
        "c2": false,
        "c3": false,
        "c4": false,
        "signal": false
      },
      "futures_price": 1036.1,
      "candle_high": 1036.9,
      "candle_low": 1035.2,
      "prev_candle_high": 1035.3,
      "prev_candle_low": 1033.7,
      "candle_time": "11:45 IST",
      "vwap": 1030.4293867780007,
      "rsi": 65.89630294120533,
      "pdi": 26.652923613152105,
      "ndi": 13.94163355261821,
      "live_price": 1036.2,
      "live_vwap": 1030.4,
      "live_rsi": 66.13506318733477,
      "live_pdi": 26.575469327187974,
      "live_ndi": 13.901118700001488,
      "atm_strike": 1000,
      "strike_step": 100
    },
    {
      "name": "SUNPHARMA",
      "sector": "Pharma",
      "lot_size": 400,
      "ce": {
        "c1": true,
        "c2": false,
        "c3": false,
        "c4": false,
        "signal": false
      },
      "pe": {
        "c1": false,
        "c2": true,
        "c3": false,
        "c4": false,
        "signal": false
      },
      "futures_price": 1908.1,
      "candle_high": 1910.0,
      "candle_low": 1907.5,
      "prev_candle_high": 1913.8,
      "prev_candle_low": 1908.7,
      "candle_time": "11:45 IST",
      "vwap": 1908.8537700400266,
      "rsi": 49.16967609969704,
      "pdi": 24.47174642378862,
      "ndi": 24.092322631927157,
      "live_price": 1908.6,
      "live_vwap": 1908.63,
      "live_rsi": 49.93315134498729,
      "live_pdi": 24.272099139851626,
      "live_ndi": 23.895770792352586,
      "atm_strike": 1900,
      "strike_step": 20
    },
    {
      "name": "LT",
      "sector": "Engineering/Infra",
      "lot_size": 175,
      "ce": {
        "c1": true,
        "c2": false,
        "c3": true,
        "c4": false,
        "signal": false
      },
      "pe": {
        "c1": false,
        "c2": false,
        "c3": false,
        "c4": false,
        "signal": false
      },
      "futures_price": 4044.0,
      "candle_high": 4046.5,
      "candle_low": 4039.9,
      "prev_candle_high": 4042.0,
      "prev_candle_low": 4038.6,
      "candle_time": "11:45 IST",
      "vwap": 4063.405218387854,
      "rsi": 40.55980806778607,
      "pdi": 20.693865341218284,
      "ndi": 31.050887889461425,
      "live_price": 4045.5,
      "live_vwap": 4063.72,
      "live_rsi": 43.12354072376325,
      "live_pdi": 20.23884376742062,
      "live_ndi": 30.368133670164582,
      "atm_strike": 4050,
      "strike_step": 50
    },
    {
      "name": "SBIN",
      "sector": "PSU Banking",
      "lot_size": 750,
      "ce": {
        "c1": false,
        "c2": false,
        "c3": false,
        "c4": false,
        "signal": false
      },
      "pe": {
        "c1": false,
        "c2": false,
        "c3": false,
        "c4": false,
        "signal": false
      },
      "futures_price": 1045.0,
      "candle_high": 1046.0,
      "candle_low": 1044.9,
      "prev_candle_high": 1045.8,
      "prev_candle_low": 1044.9,
      "candle_time": "11:45 IST",
      "vwap": 1046.7662152636537,
      "rsi": 41.93406561376127,
      "pdi": 14.411175359821112,
      "ndi": 22.275558189973736,
      "live_price": 1045.0,
      "live_vwap": 1046.86,
      "live_rsi": 41.93406561376127,
      "live_pdi": 14.411175359821113,
      "live_ndi": 22.275558189973733,
      "atm_strike": 1040,
      "strike_step": 10
    },
    {
      "name": "BHARTIARTL",
      "sector": "Telecom",
      "lot_size": 475,
      "ce": {
        "c1": false,
        "c2": false,
        "c3": false,
        "c4": false,
        "signal": false
      },
      "pe": {
        "c1": true,
        "c2": false,
        "c3": true,
        "c4": false,
        "signal": false
      },
      "futures_price": 1900.8,
      "candle_high": 1903.4,
      "candle_low": 1899.9,
      "prev_candle_high": 1905.0,
      "prev_candle_low": 1898.9,
      "candle_time": "11:45 IST",
      "vwap": 1895.3684866275235,
      "rsi": 65.00875544067608,
      "pdi": 33.9109228445375,
      "ndi": 10.041477917947116,
      "live_price": 1900.5,
      "live_vwap": 1894.81,
      "live_rsi": 64.1671677183013,
      "live_pdi": 33.672091596653566,
      "live_ndi": 9.970756790340628,
      "atm_strike": 1900,
      "strike_step": 20
    },
    {
      "name": "TATASTEEL",
      "sector": "Metals",
      "lot_size": 2750,
      "ce": {
        "c1": true,
        "c2": false,
        "c3": false,
        "c4": false,
        "signal": false
      },
      "pe": {
        "c1": false,
        "c2": false,
        "c3": false,
        "c4": false,
        "signal": false
      },
      "futures_price": 191.16,
      "candle_high": 191.3,
      "candle_low": 191.03,
      "prev_candle_high": 191.6,
      "prev_candle_low": 190.58,
      "candle_time": "11:45 IST",
      "vwap": 191.55102184143556,
      "rsi": 58.40743453402878,
      "pdi": 27.711163310671154,
      "ndi": 17.322790552127497,
      "live_price": 191.25,
      "live_vwap": 191.52,
      "live_rsi": 59.66194979079277,
      "live_pdi": 27.295903609338186,
      "live_ndi": 17.06320358530536,
      "atm_strike": 190.0,
      "strike_step": 2.5
    },
    {
      "name": "ASIANPAINT",
      "sector": "Paints/Consumer",
      "lot_size": 250,
      "ce": {
        "c1": true,
        "c2": false,
        "c3": false,
        "c4": false,
        "signal": false
      },
      "pe": {
        "c1": false,
        "c2": false,
        "c3": false,
        "c4": false,
        "signal": false
      },
      "futures_price": 2746.0,
      "candle_high": 2747.6,
      "candle_low": 2745.4,
      "prev_candle_high": 2747.5,
      "prev_candle_low": 2745.6,
      "candle_time": "11:45 IST",
      "vwap": 2748.3658947753684,
      "rsi": 49.35898880345569,
      "pdi": 19.252983870449928,
      "ndi": 17.557762900752095,
      "live_price": 2747.7,
      "live_vwap": 2748.24,
      "live_rsi": 52.776077868019776,
      "live_pdi": 18.809396101728638,
      "live_ndi": 16.975261677729964,
      "atm_strike": 2740,
      "strike_step": 20
    },
    {
      "name": "AXISBANK",
      "sector": "Private Banking",
      "lot_size": 625,
      "ce": {
        "c1": true,
        "c2": false,
        "c3": false,
        "c4": false,
        "signal": false
      },
      "pe": {
        "c1": false,
        "c2": false,
        "c3": false,
        "c4": false,
        "signal": false
      },
      "futures_price": 1355.0,
      "candle_high": 1357.6,
      "candle_low": 1355.0,
      "prev_candle_high": 1356.8,
      "prev_candle_low": 1354.8,
      "candle_time": "11:45 IST",
      "vwap": 1361.8294171122416,
      "rsi": 39.77662455695871,
      "pdi": 18.606624054630483,
      "ndi": 22.88221985664566,
      "live_price": 1355.5,
      "live_vwap": 1361.71,
      "live_rsi": 41.533783685986265,
      "live_pdi": 18.31747062482253,
      "live_ndi": 22.526622176285038,
      "atm_strike": 1360,
      "strike_step": 10
    },
    {
      "name": "MARUTI",
      "sector": "Auto",
      "lot_size": 50,
      "ce": {
        "c1": false,
        "c2": false,
        "c3": false,
        "c4": false,
        "signal": false
      },
      "pe": {
        "c1": true,
        "c2": false,
        "c3": false,
        "c4": false,
        "signal": false
      },
      "futures_price": 14436.0,
      "candle_high": 14436.0,
      "candle_low": 14417.0,
      "prev_candle_high": 14437.0,
      "prev_candle_low": 14421.0,
      "candle_time": "11:45 IST",
      "vwap": 14450.644649378151,
      "rsi": 49.078880799112575,
      "pdi": 15.899974315788018,
      "ndi": 19.12792118611184,
      "live_price": 14431.0,
      "live_vwap": 14451.11,
      "live_rsi": 47.70604009086953,
      "live_pdi": 15.678175045917273,
      "live_ndi": 18.861093147967647,
      "atm_strike": 14400,
      "strike_step": 100
    },
    {
      "name": "CIPLA",
      "sector": "Pharma",
      "lot_size": 375,
      "ce": {
        "c1": false,
        "c2": false,
        "c3": false,
        "c4": false,
        "signal": false
      },
      "pe": {
        "c1": true,
        "c2": false,
        "c3": true,
        "c4": false,
        "signal": false
      },
      "futures_price": 1460.4,
      "candle_high": 1461.1,
      "candle_low": 1459.5,
      "prev_candle_high": 1462.0,
      "prev_candle_low": 1460.1,
      "candle_time": "11:45 IST",
      "vwap": 1462.1857315884922,
      "rsi": 48.21326430490355,
      "pdi": 20.451428017751233,
      "ndi": 19.137089443807707,
      "live_price": 1458.2,
      "live_vwap": 1461.91,
      "live_rsi": 42.900692490582855,
      "live_pdi": 19.37102663991407,
      "live_ndi": 21.247756814277647,
      "atm_strike": 1460,
      "strike_step": 10
    },
    {
      "name": "HINDALCO",
      "sector": "Metals",
      "lot_size": 700,
      "ce": {
        "c1": true,
        "c2": false,
        "c3": true,
        "c4": false,
        "signal": false
      },
      "pe": {
        "c1": false,
        "c2": false,
        "c3": false,
        "c4": false,
        "signal": false
      },
      "futures_price": 963.1,
      "candle_high": 963.4,
      "candle_low": 962.3,
      "prev_candle_high": 963.7,
      "prev_candle_low": 962.6,
      "candle_time": "11:45 IST",
      "vwap": 970.749839359689,
      "rsi": 48.734333527212414,
      "pdi": 20.812137095773075,
      "ndi": 19.20251951470635,
      "live_price": 963.5,
      "live_vwap": 970.78,
      "live_rsi": 50.15554218326837,
      "live_pdi": 20.872879050109137,
      "live_ndi": 18.92400071163849,
      "atm_strike": 960,
      "strike_step": 10
    }
  ],
  "active_signals": [],
  "history": [
    {
      "time": "10:20",
      "candle_time": "10:15 IST",
      "instrument": "BAJFINANCE",
      "ce_conditions": [
        true,
        true,
        true,
        true
      ],
      "pe_conditions": [
        false,
        false,
        false,
        false
      ],
      "ce_signal": true,
      "pe_signal": false,
      "rsi": 63.734948906534555,
      "pdi": 29.979098738504884,
      "ndi": 10.962922541754473,
      "price": 1030.0
    },
    {
      "time": "09:41",
      "candle_time": "09:35 IST",
      "instrument": "SUNPHARMA",
      "ce_conditions": [
        true,
        true,
        true,
        true
      ],
      "pe_conditions": [
        false,
        false,
        false,
        false
      ],
      "ce_signal": true,
      "pe_signal": false,
      "rsi": 82.71359144974775,
      "pdi": 43.57312524983954,
      "ndi": 9.025444580509207,
      "price": 1898.3
    },
    {
      "time": "09:41",
      "candle_time": "09:35 IST",
      "instrument": "ASIANPAINT",
      "ce_conditions": [
        true,
        true,
        true,
        true
      ],
      "pe_conditions": [
        false,
        false,
        false,
        false
      ],
      "ce_signal": true,
      "pe_signal": false,
      "rsi": 54.75729780858575,
      "pdi": 25.37740847803411,
      "ndi": 25.44387063603396,
      "price": 2752.6
    }
  ]
}