{
  "date": "2026-07-14",
  "last_run": "2026-07-14T14:35:54.528087+05:30",
  "token_valid": true,
  "instruments": [
    {
      "name": "RELIANCE",
      "sector": "Energy/Conglomerate",
      "lot_size": 250,
      "ce": {
        "c1": true,
        "c2": false,
        "c3": false,
        "c4": false,
        "c5": false,
        "signal": false
      },
      "pe": {
        "c1": false,
        "c2": false,
        "c3": false,
        "c4": false,
        "c5": true,
        "signal": false
      },
      "futures_price": 1291.6,
      "candle_high": 1292.2,
      "candle_low": 1291.0,
      "prev_candle_high": 1292.5,
      "prev_candle_low": 1291.0,
      "candle_time": "14:30 IST",
      "vwap": 1299.1119947772954,
      "rsi": 29.10970261528469,
      "pdi": 6.013301244960055,
      "ndi": 28.24529071922176,
      "live_price": 1291.7,
      "live_vwap": 1299.03,
      "live_rsi": 29.66919567869708,
      "live_pdi": 5.989913346140462,
      "live_ndi": 28.135434589525143,
      "atm_strike": 1300,
      "strike_step": 50
    },
    {
      "name": "ICICIBANK",
      "sector": "Private Banking",
      "lot_size": 700,
      "ce": {
        "c1": false,
        "c2": false,
        "c3": false,
        "c4": false,
        "c5": true,
        "signal": false
      },
      "pe": {
        "c1": true,
        "c2": false,
        "c3": false,
        "c4": false,
        "c5": false,
        "signal": false
      },
      "futures_price": 1407.8,
      "candle_high": 1408.0,
      "candle_low": 1405.4,
      "prev_candle_high": 1406.7,
      "prev_candle_low": 1404.5,
      "candle_time": "14:30 IST",
      "vwap": 1403.1723578224883,
      "rsi": 61.682552534034095,
      "pdi": 21.717493388286982,
      "ndi": 17.345574215730206,
      "live_price": 1407.2,
      "live_vwap": 1403.1,
      "live_rsi": 58.57669782719722,
      "live_pdi": 21.277516151587555,
      "live_ndi": 16.994168200498358,
      "atm_strike": 1400,
      "strike_step": 20
    },
    {
      "name": "INFY",
      "sector": "IT",
      "lot_size": 400,
      "ce": {
        "c1": false,
        "c2": false,
        "c3": false,
        "c4": false,
        "c5": false,
        "signal": false
      },
      "pe": {
        "c1": false,
        "c2": false,
        "c3": false,
        "c4": false,
        "c5": true,
        "signal": false
      },
      "futures_price": 1096.9,
      "candle_high": 1096.9,
      "candle_low": 1094.5,
      "prev_candle_high": 1097.5,
      "prev_candle_low": 1095.0,
      "candle_time": "14:30 IST",
      "vwap": 1100.1099175563852,
      "rsi": 57.061787085898175,
      "pdi": 17.506694703135864,
      "ndi": 17.076542566620148,
      "live_price": 1096.9,
      "live_vwap": 1100.41,
      "live_rsi": 57.061787085898175,
      "live_pdi": 17.506694703135864,
      "live_ndi": 17.07654256662015,
      "atm_strike": 1100,
      "strike_step": 20
    },
    {
      "name": "BAJFINANCE",
      "sector": "NBFC",
      "lot_size": 125,
      "ce": {
        "c1": true,
        "c2": false,
        "c3": true,
        "c4": true,
        "c5": false,
        "signal": false
      },
      "pe": {
        "c1": false,
        "c2": false,
        "c3": false,
        "c4": false,
        "c5": true,
        "signal": false
      },
      "futures_price": 1010.5,
      "candle_high": 1010.5,
      "candle_low": 1009.1,
      "prev_candle_high": 1010.0,
      "prev_candle_low": 1009.0,
      "candle_time": "14:30 IST",
      "vwap": 1003.984271079147,
      "rsi": 64.02023783447513,
      "pdi": 26.292737300661198,
      "ndi": 6.6798674998305065,
      "live_price": 1010.8,
      "live_vwap": 1003.68,
      "live_rsi": 65.2460574843485,
      "live_pdi": 27.44654396958542,
      "live_ndi": 6.5753014721885155,
      "atm_strike": 1000,
      "strike_step": 100
    },
    {
      "name": "SUNPHARMA",
      "sector": "Pharma",
      "lot_size": 400,
      "ce": {
        "c1": true,
        "c2": false,
        "c3": true,
        "c4": false,
        "c5": true,
        "signal": false
      },
      "pe": {
        "c1": false,
        "c2": false,
        "c3": false,
        "c4": false,
        "c5": false,
        "signal": false
      },
      "futures_price": 1947.8,
      "candle_high": 1948.8,
      "candle_low": 1945.6,
      "prev_candle_high": 1950.8,
      "prev_candle_low": 1945.6,
      "candle_time": "14:30 IST",
      "vwap": 1941.2715151328155,
      "rsi": 59.939967369700156,
      "pdi": 21.886028767863635,
      "ndi": 9.233292309065924,
      "live_price": 1950.2,
      "live_vwap": 1939.94,
      "live_rsi": 64.8172167593882,
      "live_pdi": 23.78702360587963,
      "live_ndi": 8.751708246082687,
      "atm_strike": 1940,
      "strike_step": 20
    },
    {
      "name": "LT",
      "sector": "Engineering/Infra",
      "lot_size": 175,
      "ce": {
        "c1": false,
        "c2": false,
        "c3": false,
        "c4": false,
        "c5": false,
        "signal": false
      },
      "pe": {
        "c1": true,
        "c2": false,
        "c3": false,
        "c4": false,
        "c5": true,
        "signal": false
      },
      "futures_price": 3848.7,
      "candle_high": 3849.7,
      "candle_low": 3846.8,
      "prev_candle_high": 3850.0,
      "prev_candle_low": 3845.5,
      "candle_time": "14:30 IST",
      "vwap": 3863.1009748537317,
      "rsi": 34.883708110296524,
      "pdi": 3.345558215575926,
      "ndi": 27.952493682937313,
      "live_price": 3848.5,
      "live_vwap": 3863.12,
      "live_rsi": 34.42078701517357,
      "live_pdi": 3.32938887976046,
      "live_ndi": 27.817397167463504,
      "atm_strike": 3850,
      "strike_step": 50
    },
    {
      "name": "BHARTIARTL",
      "sector": "Telecom",
      "lot_size": 475,
      "ce": {
        "c1": false,
        "c2": false,
        "c3": false,
        "c4": false,
        "c5": true,
        "signal": false
      },
      "pe": {
        "c1": true,
        "c2": false,
        "c3": false,
        "c4": false,
        "c5": false,
        "signal": false
      },
      "futures_price": 1939.0,
      "candle_high": 1939.0,
      "candle_low": 1936.7,
      "prev_candle_high": 1939.0,
      "prev_candle_low": 1935.5,
      "candle_time": "14:30 IST",
      "vwap": 1930.0203353693823,
      "rsi": 59.44333820392801,
      "pdi": 17.47729155142502,
      "ndi": 15.187649048336288,
      "live_price": 1938.6,
      "live_vwap": 1928.58,
      "live_rsi": 58.115489383238184,
      "live_pdi": 17.29763951759747,
      "live_ndi": 15.031532636787945,
      "atm_strike": 1940,
      "strike_step": 20
    },
    {
      "name": "TATASTEEL",
      "sector": "Metals",
      "lot_size": 2750,
      "ce": {
        "c1": true,
        "c2": false,
        "c3": true,
        "c4": false,
        "c5": false,
        "signal": false
      },
      "pe": {
        "c1": false,
        "c2": false,
        "c3": false,
        "c4": false,
        "c5": true,
        "signal": false
      },
      "futures_price": 187.78,
      "candle_high": 187.8,
      "candle_low": 187.6,
      "prev_candle_high": 187.93,
      "prev_candle_low": 187.7,
      "candle_time": "14:30 IST",
      "vwap": 188.8395675448732,
      "rsi": 33.57740200479944,
      "pdi": 10.15406168698614,
      "ndi": 32.42371883897289,
      "live_price": 187.91,
      "live_vwap": 188.83,
      "live_rsi": 37.64829972284289,
      "live_pdi": 12.343423762002027,
      "live_ndi": 31.470374773016736,
      "atm_strike": 187.5,
      "strike_step": 2.5
    },
    {
      "name": "ASIANPAINT",
      "sector": "Paints/Consumer",
      "lot_size": 250,
      "ce": {
        "c1": true,
        "c2": true,
        "c3": false,
        "c4": false,
        "c5": false,
        "signal": false
      },
      "pe": {
        "c1": false,
        "c2": false,
        "c3": false,
        "c4": false,
        "c5": true,
        "signal": false
      },
      "futures_price": 2640.8,
      "candle_high": 2641.7,
      "candle_low": 2638.3,
      "prev_candle_high": 2642.6,
      "prev_candle_low": 2638.5,
      "candle_time": "14:30 IST",
      "vwap": 2640.0303549665564,
      "rsi": 41.01267631168608,
      "pdi": 16.461157197387003,
      "ndi": 28.304320456776573,
      "live_price": 2642.1,
      "live_vwap": 2639.27,
      "live_rsi": 44.15182928418366,
      "live_pdi": 16.83143864404114,
      "live_ndi": 27.571827387555025,
      "atm_strike": 2640,
      "strike_step": 20
    },
    {
      "name": "AXISBANK",
      "sector": "Private Banking",
      "lot_size": 625,
      "ce": {
        "c1": false,
        "c2": false,
        "c3": false,
        "c4": false,
        "c5": true,
        "signal": false
      },
      "pe": {
        "c1": true,
        "c2": false,
        "c3": false,
        "c4": false,
        "c5": false,
        "signal": false
      },
      "futures_price": 1317.7,
      "candle_high": 1318.1,
      "candle_low": 1315.0,
      "prev_candle_high": 1316.6,
      "prev_candle_low": 1315.1,
      "candle_time": "14:30 IST",
      "vwap": 1309.9155683339436,
      "rsi": 65.74143266621675,
      "pdi": 27.051752757949203,
      "ndi": 14.34599423383478,
      "live_price": 1317.2,
      "live_vwap": 1309.87,
      "live_rsi": 64.04300889364202,
      "live_pdi": 26.69672662711755,
      "live_ndi": 14.15771797420222,
      "atm_strike": 1320,
      "strike_step": 10
    },
    {
      "name": "MARUTI",
      "sector": "Auto",
      "lot_size": 50,
      "ce": {
        "c1": true,
        "c2": false,
        "c3": false,
        "c4": false,
        "c5": false,
        "signal": false
      },
      "pe": {
        "c1": false,
        "c2": false,
        "c3": false,
        "c4": false,
        "c5": true,
        "signal": false
      },
      "futures_price": 13513.0,
      "candle_high": 13530.0,
      "candle_low": 13503.0,
      "prev_candle_high": 13533.0,
      "prev_candle_low": 13525.0,
      "candle_time": "14:30 IST",
      "vwap": 13545.305912140968,
      "rsi": 42.971549514479,
      "pdi": 12.198582150912634,
      "ndi": 22.576726228416614,
      "live_price": 13519.0,
      "live_vwap": 13544.95,
      "live_rsi": 46.13457205864189,
      "live_pdi": 11.909603354561074,
      "live_ndi": 22.04189397575532,
      "atm_strike": 13500,
      "strike_step": 100
    },
    {
      "name": "CIPLA",
      "sector": "Pharma",
      "lot_size": 375,
      "ce": {
        "c1": false,
        "c2": false,
        "c3": false,
        "c4": false,
        "c5": false,
        "signal": false
      },
      "pe": {
        "c1": true,
        "c2": false,
        "c3": false,
        "c4": false,
        "c5": true,
        "signal": false
      },
      "futures_price": 1443.3,
      "candle_high": 1443.4,
      "candle_low": 1441.7,
      "prev_candle_high": 1444.3,
      "prev_candle_low": 1441.6,
      "candle_time": "14:30 IST",
      "vwap": 1447.382884506184,
      "rsi": 41.25783354532573,
      "pdi": 10.5075779679695,
      "ndi": 23.915111461194282,
      "live_price": 1443.1,
      "live_vwap": 1447.31,
      "live_rsi": 40.723414873340346,
      "live_pdi": 10.44096636537309,
      "live_ndi": 23.763504315802834,
      "atm_strike": 1440,
      "strike_step": 10
    },
    {
      "name": "HINDALCO",
      "sector": "Metals",
      "lot_size": 700,
      "ce": {
        "c1": false,
        "c2": false,
        "c3": false,
        "c4": false,
        "c5": false,
        "signal": false
      },
      "pe": {
        "c1": true,
        "c2": false,
        "c3": true,
        "c4": false,
        "c5": true,
        "signal": false
      },
      "futures_price": 975.1,
      "candle_high": 976.3,
      "candle_low": 974.6,
      "prev_candle_high": 979.0,
      "prev_candle_low": 976.1,
      "candle_time": "14:30 IST",
      "vwap": 985.295487576964,
      "rsi": 27.5013895147126,
      "pdi": 17.41610933518691,
      "ndi": 31.217546187920505,
      "live_price": 975.0,
      "live_vwap": 985.32,
      "live_rsi": 27.27631470177944,
      "live_pdi": 17.34246124548053,
      "live_ndi": 31.085535496105653,
      "atm_strike": 980,
      "strike_step": 10
    }
  ],
  "active_signals": [],
  "history": [
    {
      "time": "14:25",
      "candle_time": "14:20 IST",
      "instrument": "ASIANPAINT",
      "ce_conditions": [
        false,
        false,
        false,
        false,
        false
      ],
      "pe_conditions": [
        true,
        true,
        true,
        true,
        true
      ],
      "ce_signal": false,
      "pe_signal": true,
      "rsi": 37.66704620985741,
      "pdi": 19.069136157758916,
      "ndi": 30.307736799719553,
      "price": 2639.5
    },
    {
      "time": "10:45",
      "candle_time": "10:40 IST",
      "instrument": "ICICIBANK",
      "ce_conditions": [
        true,
        true,
        true,
        true,
        false
      ],
      "pe_conditions": [
        false,
        false,
        false,
        false,
        true
      ],
      "ce_signal": true,
      "pe_signal": false,
      "rsi": 53.182470520560514,
      "pdi": 25.547074898927953,
      "ndi": 25.09889692578941,
      "price": 1400.3
    },
    {
      "time": "10:31",
      "candle_time": "10:25 IST",
      "instrument": "INFY",
      "ce_conditions": [
        true,
        true,
        true,
        true,
        false
      ],
      "pe_conditions": [
        false,
        false,
        false,
        false,
        true
      ],
      "ce_signal": true,
      "pe_signal": false,
      "rsi": 55.10940946254531,
      "pdi": 28.476115348644353,
      "ndi": 22.758868313386262,
      "price": 1102.9
    },
    {
      "time": "10:15",
      "candle_time": "10:10 IST",
      "instrument": "TATASTEEL",
      "ce_conditions": [
        true,
        true,
        true,
        true,
        true
      ],
      "pe_conditions": [
        false,
        false,
        false,
        false,
        false
      ],
      "ce_signal": true,
      "pe_signal": false,
      "rsi": 58.4335960790543,
      "pdi": 29.851396069153907,
      "ndi": 16.848595394055607,
      "price": 188.55
    }
  ]
}