{
  "date": "2026-06-29",
  "last_run": "2026-06-29T11:01:19.769185+05:30",
  "token_valid": true,
  "instruments": [
    {
      "name": "RELIANCE",
      "sector": "Energy/Conglomerate",
      "lot_size": 250,
      "ce": {
        "c1": false,
        "c2": false,
        "c3": false,
        "c4": false,
        "signal": false
      },
      "pe": {
        "c1": true,
        "c2": false,
        "c3": false,
        "c4": false,
        "signal": false
      },
      "futures_price": 1308.0,
      "candle_high": 1308.5,
      "candle_low": 1307.1,
      "prev_candle_high": 1308.9,
      "prev_candle_low": 1307.0,
      "candle_time": "10:55 IST",
      "vwap": 1310.0846308677044,
      "rsi": 33.874952803892555,
      "pdi": 11.534968860730423,
      "ndi": 34.4689056145383,
      "live_price": 1307.7,
      "live_vwap": 1309.8,
      "live_rsi": 33.08538015407541,
      "live_pdi": 11.409849352870557,
      "live_ndi": 34.09502228992514,
      "atm_strike": 1300,
      "strike_step": 50
    },
    {
      "name": "ICICIBANK",
      "sector": "Private Banking",
      "lot_size": 700,
      "ce": {
        "c1": true,
        "c2": false,
        "c3": false,
        "c4": false,
        "signal": false
      },
      "pe": {
        "c1": false,
        "c2": false,
        "c3": false,
        "c4": false,
        "signal": false
      },
      "futures_price": 1387.8,
      "candle_high": 1389.1,
      "candle_low": 1387.4,
      "prev_candle_high": 1390.4,
      "prev_candle_low": 1387.5,
      "candle_time": "10:55 IST",
      "vwap": 1391.2883226513468,
      "rsi": 45.94978833978632,
      "pdi": 17.77058579850213,
      "ndi": 22.684891975514077,
      "live_price": 1388.4,
      "live_vwap": 1391.53,
      "live_rsi": 47.39733415691291,
      "live_pdi": 17.4823412784775,
      "live_ndi": 22.316935855584493,
      "atm_strike": 1380,
      "strike_step": 20
    },
    {
      "name": "INFY",
      "sector": "IT",
      "lot_size": 400,
      "ce": {
        "c1": true,
        "c2": false,
        "c3": false,
        "c4": false,
        "signal": false
      },
      "pe": {
        "c1": false,
        "c2": false,
        "c3": false,
        "c4": false,
        "signal": false
      },
      "futures_price": 1033.7,
      "candle_high": 1034.9,
      "candle_low": 1033.0,
      "prev_candle_high": 1034.9,
      "prev_candle_low": 1033.5,
      "candle_time": "10:55 IST",
      "vwap": 1034.9126613816334,
      "rsi": 42.866435833567046,
      "pdi": 20.414577344154466,
      "ndi": 27.36720481193419,
      "live_price": 1034.0,
      "live_vwap": 1035.35,
      "live_rsi": 43.71325345012414,
      "live_pdi": 20.250099433402823,
      "live_ndi": 27.146710378241284,
      "atm_strike": 1040,
      "strike_step": 20
    },
    {
      "name": "BAJFINANCE",
      "sector": "NBFC",
      "lot_size": 125,
      "ce": {
        "c1": false,
        "c2": false,
        "c3": false,
        "c4": false,
        "signal": false
      },
      "pe": {
        "c1": true,
        "c2": false,
        "c3": false,
        "c4": false,
        "signal": false
      },
      "futures_price": 987.8,
      "candle_high": 988.8,
      "candle_low": 987.05,
      "prev_candle_high": 988.35,
      "prev_candle_low": 987.1,
      "candle_time": "10:55 IST",
      "vwap": 985.9899133919417,
      "rsi": 57.762286938967726,
      "pdi": 25.761759456892452,
      "ndi": 14.941584814699434,
      "live_price": 987.4,
      "live_vwap": 985.19,
      "live_rsi": 56.01208930872259,
      "live_pdi": 25.42841722967865,
      "live_ndi": 14.748249372352413,
      "atm_strike": 1000,
      "strike_step": 100
    },
    {
      "name": "SUNPHARMA",
      "sector": "Pharma",
      "lot_size": 400,
      "ce": {
        "c1": true,
        "c2": false,
        "c3": false,
        "c4": false,
        "signal": false
      },
      "pe": {
        "c1": false,
        "c2": false,
        "c3": false,
        "c4": false,
        "signal": false
      },
      "futures_price": 1889.4,
      "candle_high": 1891.0,
      "candle_low": 1888.9,
      "prev_candle_high": 1891.9,
      "prev_candle_low": 1889.2,
      "candle_time": "10:55 IST",
      "vwap": 1887.9323366507554,
      "rsi": 56.64561298052191,
      "pdi": 23.907651643614063,
      "ndi": 13.172087549026273,
      "live_price": 1889.7,
      "live_vwap": 1887.25,
      "live_rsi": 57.10514605330084,
      "live_pdi": 23.774697750781442,
      "live_ndi": 13.098835673748807,
      "atm_strike": 1880,
      "strike_step": 20
    },
    {
      "name": "LT",
      "sector": "Engineering/Infra",
      "lot_size": 175,
      "ce": {
        "c1": false,
        "c2": false,
        "c3": false,
        "c4": false,
        "signal": false
      },
      "pe": {
        "c1": true,
        "c2": false,
        "c3": true,
        "c4": false,
        "signal": false
      },
      "futures_price": 4215.1,
      "candle_high": 4218.3,
      "candle_low": 4213.3,
      "prev_candle_high": 4220.1,
      "prev_candle_low": 4209.3,
      "candle_time": "10:55 IST",
      "vwap": 4228.006056983396,
      "rsi": 43.76058747863583,
      "pdi": 20.76667230140503,
      "ndi": 29.457609930954145,
      "live_price": 4214.8,
      "live_vwap": 4228.21,
      "live_rsi": 43.606359551373494,
      "live_pdi": 20.72620649715588,
      "live_ndi": 29.4002090214674,
      "atm_strike": 4200,
      "strike_step": 50
    },
    {
      "name": "SBIN",
      "sector": "PSU Banking",
      "lot_size": 750,
      "ce": {
        "c1": false,
        "c2": false,
        "c3": false,
        "c4": false,
        "signal": false
      },
      "pe": {
        "c1": true,
        "c2": true,
        "c3": false,
        "c4": false,
        "signal": false
      },
      "futures_price": 1042.75,
      "candle_high": 1043.2,
      "candle_low": 1041.6,
      "prev_candle_high": 1043.95,
      "prev_candle_low": 1041.5,
      "candle_time": "10:55 IST",
      "vwap": 1042.6587262465737,
      "rsi": 46.90028817051935,
      "pdi": 19.01951616830904,
      "ndi": 20.309079345896507,
      "live_price": 1042.2,
      "live_vwap": 1042.8,
      "live_rsi": 45.38312945926335,
      "live_pdi": 18.6710591480342,
      "live_ndi": 19.936996207147264,
      "atm_strike": 1040,
      "strike_step": 10
    },
    {
      "name": "BHARTIARTL",
      "sector": "Telecom",
      "lot_size": 475,
      "ce": {
        "c1": false,
        "c2": false,
        "c3": false,
        "c4": false,
        "signal": false
      },
      "pe": {
        "c1": true,
        "c2": false,
        "c3": true,
        "c4": false,
        "signal": false
      },
      "futures_price": 1833.9,
      "candle_high": 1835.1,
      "candle_low": 1833.1,
      "prev_candle_high": 1835.8,
      "prev_candle_low": 1833.5,
      "candle_time": "10:55 IST",
      "vwap": 1842.2144571576146,
      "rsi": 27.002832695596652,
      "pdi": 12.561677509715835,
      "ndi": 33.966630179759065,
      "live_price": 1833.6,
      "live_vwap": 1841.34,
      "live_rsi": 26.644971405548617,
      "live_pdi": 12.473492490107466,
      "live_ndi": 33.72817891032347,
      "atm_strike": 1840,
      "strike_step": 20
    },
    {
      "name": "TATASTEEL",
      "sector": "Metals",
      "lot_size": 2750,
      "ce": {
        "c1": false,
        "c2": false,
        "c3": false,
        "c4": false,
        "signal": false
      },
      "pe": {
        "c1": true,
        "c2": false,
        "c3": false,
        "c4": false,
        "signal": false
      },
      "futures_price": 190.25,
      "candle_high": 190.39,
      "candle_low": 190.12,
      "prev_candle_high": 190.3,
      "prev_candle_low": 190.11,
      "candle_time": "10:55 IST",
      "vwap": 190.17369383140533,
      "rsi": 55.116326384499,
      "pdi": 27.099588035228738,
      "ndi": 16.260661203288272,
      "live_price": 190.14,
      "live_vwap": 190.14,
      "live_rsi": 53.06801963762574,
      "live_pdi": 26.622928540374275,
      "live_ndi": 15.974649528679674,
      "atm_strike": 190.0,
      "strike_step": 2.5
    },
    {
      "name": "ASIANPAINT",
      "sector": "Paints/Consumer",
      "lot_size": 250,
      "ce": {
        "c1": false,
        "c2": false,
        "c3": false,
        "c4": false,
        "signal": false
      },
      "pe": {
        "c1": true,
        "c2": false,
        "c3": false,
        "c4": false,
        "signal": false
      },
      "futures_price": 2647.7,
      "candle_high": 2648.9,
      "candle_low": 2645.3,
      "prev_candle_high": 2654.1,
      "prev_candle_low": 2645.0,
      "candle_time": "10:55 IST",
      "vwap": 2667.72125484481,
      "rsi": 36.11650289711376,
      "pdi": 13.480159484047737,
      "ndi": 31.770073961469453,
      "live_price": 2646.9,
      "live_vwap": 2667.29,
      "live_rsi": 35.52436714936762,
      "live_pdi": 13.358589459627892,
      "live_ndi": 31.483557420482917,
      "atm_strike": 2640,
      "strike_step": 20
    },
    {
      "name": "AXISBANK",
      "sector": "Private Banking",
      "lot_size": 625,
      "ce": {
        "c1": false,
        "c2": false,
        "c3": false,
        "c4": false,
        "signal": false
      },
      "pe": {
        "c1": true,
        "c2": true,
        "c3": true,
        "c4": false,
        "signal": false
      },
      "futures_price": 1386.0,
      "candle_high": 1387.5,
      "candle_low": 1385.8,
      "prev_candle_high": 1387.9,
      "prev_candle_low": 1381.8,
      "candle_time": "10:55 IST",
      "vwap": 1385.235073934374,
      "rsi": 52.72359435399501,
      "pdi": 23.340160489487495,
      "ndi": 21.901440347879355,
      "live_price": 1385.0,
      "live_vwap": 1386.28,
      "live_rsi": 50.693024355820505,
      "live_pdi": 22.861790602853738,
      "live_ndi": 23.092203427974084,
      "atm_strike": 1390,
      "strike_step": 10
    },
    {
      "name": "MARUTI",
      "sector": "Auto",
      "lot_size": 50,
      "ce": {
        "c1": false,
        "c2": false,
        "c3": false,
        "c4": false,
        "signal": false
      },
      "pe": {
        "c1": true,
        "c2": false,
        "c3": false,
        "c4": false,
        "signal": false
      },
      "futures_price": 13626.0,
      "candle_high": 13636.0,
      "candle_low": 13620.0,
      "prev_candle_high": 13638.0,
      "prev_candle_low": 13621.0,
      "candle_time": "10:55 IST",
      "vwap": 13712.39897783088,
      "rsi": 29.065069166533675,
      "pdi": 9.92282040321873,
      "ndi": 28.365345636273677,
      "live_price": 13615.0,
      "live_vwap": 13713.82,
      "live_rsi": 27.385022639546904,
      "live_pdi": 9.650381365584224,
      "live_ndi": 28.834543400945854,
      "atm_strike": 13600,
      "strike_step": 100
    },
    {
      "name": "CIPLA",
      "sector": "Pharma",
      "lot_size": 375,
      "ce": {
        "c1": true,
        "c2": false,
        "c3": false,
        "c4": false,
        "signal": false
      },
      "pe": {
        "c1": false,
        "c2": false,
        "c3": false,
        "c4": false,
        "signal": false
      },
      "futures_price": 1478.5,
      "candle_high": 1479.2,
      "candle_low": 1476.1,
      "prev_candle_high": 1479.9,
      "prev_candle_low": 1477.1,
      "candle_time": "10:55 IST",
      "vwap": 1475.2454175840774,
      "rsi": 63.02840721004599,
      "pdi": 30.859962984273366,
      "ndi": 17.493636240753098,
      "live_price": 1479.0,
      "live_vwap": 1474.93,
      "live_rsi": 63.53599625225762,
      "live_pdi": 30.61086313125745,
      "live_ndi": 17.35242861135619,
      "atm_strike": 1480,
      "strike_step": 10
    },
    {
      "name": "HINDALCO",
      "sector": "Metals",
      "lot_size": 700,
      "ce": {
        "c1": false,
        "c2": false,
        "c3": false,
        "c4": false,
        "signal": false
      },
      "pe": {
        "c1": true,
        "c2": false,
        "c3": true,
        "c4": false,
        "signal": false
      },
      "futures_price": 967.3,
      "candle_high": 968.1,
      "candle_low": 967.0,
      "prev_candle_high": 968.3,
      "prev_candle_low": 965.5,
      "candle_time": "10:55 IST",
      "vwap": 961.9786208489464,
      "rsi": 64.87097026801118,
      "pdi": 29.14020175539145,
      "ndi": 15.359779593726794,
      "live_price": 965.8,
      "live_vwap": 961.25,
      "live_rsi": 59.064741353360596,
      "live_pdi": 27.712948391498948,
      "live_ndi": 18.525782794117845,
      "atm_strike": 970,
      "strike_step": 10
    }
  ],
  "active_signals": [],
  "history": [
    {
      "time": "10:51",
      "candle_time": "10:45 IST",
      "instrument": "RELIANCE",
      "ce_conditions": [
        false,
        false,
        false,
        false
      ],
      "pe_conditions": [
        true,
        true,
        true,
        true
      ],
      "ce_signal": false,
      "pe_signal": true,
      "rsi": 35.59666594056793,
      "pdi": 12.9229248252954,
      "ndi": 32.26059194695167,
      "price": 1308.8
    },
    {
      "time": "10:35",
      "candle_time": "10:30 IST",
      "instrument": "INFY",
      "ce_conditions": [
        false,
        false,
        false,
        false
      ],
      "pe_conditions": [
        true,
        true,
        true,
        true
      ],
      "ce_signal": false,
      "pe_signal": true,
      "rsi": 45.017758076319886,
      "pdi": 24.980564605655918,
      "ndi": 25.668602569126897,
      "price": 1035.2
    },
    {
      "time": "10:25",
      "candle_time": "10:20 IST",
      "instrument": "AXISBANK",
      "ce_conditions": [
        true,
        true,
        true,
        true
      ],
      "pe_conditions": [
        false,
        false,
        false,
        false
      ],
      "ce_signal": true,
      "pe_signal": false,
      "rsi": 63.14183536553819,
      "pdi": 32.81689407613039,
      "ndi": 10.88676971324907,
      "price": 1390.3
    }
  ]
}